hashfunctions/__init__.py
hashfunctions/hashfunctions.py
hashfunctions/hashtables.py
HashFunction-0.0.2.dist-info/LICENSE
HashFunction-0.0.2.dist-info/METADATA
HashFunction-0.0.2.dist-info/WHEEL
HashFunction-0.0.2.dist-info/top_level.txt
HashFunction-0.0.2.dist-info/RECORD
