Metadata-Version: 2.1
Name: HashFunction
Version: 0.0.2
Summary: Hashing module
Home-page: https://github.com/ccr5/hashing-python-module
Author: Matheus Nobre Gomes
Author-email: matt-gomes@live.com
License: GPLv3+
Keywords: hashing,hash,function
Platform: UNKNOWN
Classifier: Programming Language :: Python :: 3
Classifier: License :: OSI Approved :: GNU General Public License v3 or later (GPLv3+)
Classifier: Operating System :: OS Independent
